[
    {
        "offer_id": 2,
        "restaurant_id": 1,
        "title": "Free Miso Soup",
        "description": "Receive a free Miso Soup with purchase.",
        "offer_type": 2,
        "applied_items": [
            4
        ],
        "discount_value": null,
        "price_ceiling": null,
        "start_date": "2026-04-09T04:01:15.335988",
        "end_date": "2026-04-16T04:01:15.335988",
        "is_active": false
    },
    {
        "offer_id": 6,
        "restaurant_id": 3,
        "title": "Pizza Promo - 20% off",
        "description": "Enjoy 20% off Margherita Pizza for a limited time.",
        "offer_type": 1,
        "applied_items": [
            1
        ],
        "discount_value": 20.0,
        "price_ceiling": null,
        "start_date": "2026-04-09T04:01:15.335988",
        "end_date": "2026-04-16T04:01:15.335988",
        "is_active": false
    },
    {
        "offer_id": 7,
        "restaurant_id": 4,
        "title": "Butter Chicken Discount - 12.5%",
        "description": "12.5% off Butter Chicken orders over $20.",
        "offer_type": 1,
        "applied_items": [
            1
        ],
        "discount_value": 12.5,
        "price_ceiling": null,
        "start_date": "2026-04-09T04:01:15.335988",
        "end_date": "2026-04-16T04:01:15.335988",
        "is_active": false
    },
    {
        "offer_id": 9,
        "restaurant_id": 5,
        "title": "Healthy Combo - $10",
        "description": "Quinoa Power Bowl combo for a fixed total of $10.",
        "offer_type": 3,
        "applied_items": [
            2
        ],
        "discount_value": null,
        "price_ceiling": 10.0,
        "start_date": "2026-04-09T04:01:15.335988",
        "end_date": "2026-04-16T04:01:15.335988",
        "is_active": false
    }
]